fastapi_helper/__init__.py
fastapi_helper/authorization/__init__.py
fastapi_helper/authorization/cookies_jwt_http_bearer.py
fastapi_helper/authorization/headers_jwt_http_bearer.py
fastapi_helper/exceptions/__init__.py
fastapi_helper/exceptions/auth_http_exceptions.py
fastapi_helper/exceptions/http_exceptions.py
fastapi_helper/exceptions/validation_exceptions.py
fastapi_helper/schemas/__init__.py
fastapi_helper/schemas/camel_schema.py
fastapi_helper/schemas/examples_generate.py
fastapi_helper/sqlalchemy/__init__.py
fastapi_helper/sqlalchemy/sqlalchemy_media_utils.py
fastapi_helper/sqlalchemy/storage.py
fastapi_helper/utilities/__init__.py
fastapi_helper/utilities/password_helper.py
fastapi_helper-0.0.12.dist-info/LICENSE.txt
fastapi_helper-0.0.12.dist-info/METADATA
fastapi_helper-0.0.12.dist-info/WHEEL
fastapi_helper-0.0.12.dist-info/entry_points.txt
fastapi_helper-0.0.12.dist-info/top_level.txt
fastapi_helper-0.0.12.dist-info/RECORD
