Metadata-Version: 2.1
Name: fastapi-helper
Version: 0.0.12
Summary: Package for useful fastapi utils
Home-page: https://github.com/Rey092/fastapi-helper
Author: Rey
Author-email: roman.cheburan@gmail.com
Project-URL: Source, https://github.com/Rey092/fastapi-helper
Keywords: fastapi,utils,backend,api
Classifier: Development Status :: 3 - Alpha
Classifier: Intended Audience :: Developers
Classifier: Topic :: Software Development :: Build Tools
Classifier: License :: OSI Approved :: MIT License
Classifier: Programming Language :: Python :: 3
Classifier: Programming Language :: Python :: 3.7
Classifier: Programming Language :: Python :: 3.8
Classifier: Programming Language :: Python :: 3.9
Classifier: Programming Language :: Python :: 3.10
Classifier: Programming Language :: Python :: 3 :: Only
Requires-Python: >=3.7, <4
License-File: LICENSE.txt
Requires-Dist: fastapi
Requires-Dist: pydantic
Provides-Extra: dev
Requires-Dist: check-manifest ; extra == 'dev'
Provides-Extra: test
Requires-Dist: coverage ; extra == 'test'
